asyncpg_connector/__init__.py
asyncpg_connector/error/__init__.py
asyncpg_connector/error/error_models.py
asyncpg_connector/main.py
asyncpg_connector/model/__init__.py
asyncpg_connector/model/models.py
asyncpg_connector-0.1.2.dist-info/LICENSE
asyncpg_connector-0.1.2.dist-info/METADATA
asyncpg_connector-0.1.2.dist-info/WHEEL
asyncpg_connector-0.1.2.dist-info/RECORD
