Metadata-Version: 2.1
Name: asyncpg-connector
Version: 0.1.2
Summary: 
Author: TY
Author-email: tyyyy66@icloud.com
Requires-Python: >=3.9,<4.0
Classifier: Programming Language :: Python :: 3
Classifier: Programming Language :: Python :: 3.9
Classifier: Programming Language :: Python :: 3.10
Classifier: Programming Language :: Python :: 3.11
Classifier: Programming Language :: Python :: 3.12
Requires-Dist: asyncpg (>=0.30.0,<0.31.0)
Requires-Dist: pydantic (>=2.11.3,<3.0.0)
